MANIFEST.in
README.rst
setup.py
onyx/__init__.py
onyx/app.py
onyx/config_example.py
onyx/decorators.py
onyx/extensions.py
onyx/main.py
onyx/tasks.py
onyx/wsgi.py
onyx/api/__init__.py
onyx/api/__init__.pyc
onyx/api/action/__init__.py
onyx/api/action/__init__.pyc
onyx/api/assets/__init__.py
onyx/api/assets/__init__.pyc
onyx/api/bot/__init__.py
onyx/api/bot/__init__.pyc
onyx/api/calendar/__init__.py
onyx/api/calendar/__init__.pyc
onyx/api/events/__init__.py
onyx/api/events/__init__.pyc
onyx/api/exceptions/__init__.py
onyx/api/exceptions/__init__.pyc
onyx/api/geolocalisation/__init__.py
onyx/api/geolocalisation/__init__.pyc
onyx/api/house/__init__.py
onyx/api/house/__init__.pyc
onyx/api/install/__init__.py
onyx/api/install/__init__.pyc
onyx/api/machine/__init__.py
onyx/api/machine/__init__.pyc
onyx/api/navbar/__init__.py
onyx/api/navbar/__init__.pyc
onyx/api/notification/__init__.py
onyx/api/notification/__init__.pyc
onyx/api/options/__init__.py
onyx/api/options/__init__.pyc
onyx/api/plugins/__init__.py
onyx/api/plugins/__init__.pyc
onyx/api/room/__init__.py
onyx/api/room/__init__.pyc
onyx/api/scenario/__init__.py
onyx/api/scenario/__init__.pyc
onyx/api/server/__init__.py
onyx/api/server/__init__.pyc
onyx/api/skills/__init__.py
onyx/api/skills/__init__.pyc
onyx/api/time/__init__.py
onyx/api/time/__init__.pyc
onyx/api/transport/__init__.py
onyx/api/transport/__init__.pyc
onyx/api/user/__init__.py
onyx/api/user/__init__.pyc
onyx/api/weather/__init__.py
onyx/api/weather/__init__.pyc
onyx/api/widgets/__init__.py
onyx/api/widgets/__init__.pyc
onyx/api/wiki/__init__.py
onyx/api/wiki/__init__.pyc
onyx/client/__init__.py
onyx/client/__init__.pyc
onyx/client/speech/Onyx.pmdl
onyx/client/speech/__init__.py
onyx/client/speech/main.py
onyx/client/speech/assets/__init__.py
onyx/client/speech/assets/_snowboydetect.so
onyx/client/speech/assets/snowboydecoder.py
onyx/client/speech/assets/snowboydetect.py
onyx/client/speech/resources/common.res
onyx/client/speech/resources/ding.wav
onyxproject.egg-info/PKG-INFO
onyxproject.egg-info/SOURCES.txt
onyxproject.egg-info/dependency_links.txt
onyxproject.egg-info/entry_points.txt
onyxproject.egg-info/requires.txt
onyxproject.egg-info/top_level.txt
onyxproject.egg-info/zip-safe