Metadata-Version: 1.1
Name: onyxproject
Version: 0.9.0
Summary: Intelligent Dashboard
Home-page: https://github.com/OnyxProject/Onyx
Author: Aituglo
Author-email: ckhouani@live.fr
License: UNKNOWN
Platform: any
Classifier: Development Status :: 5 - Production/Stable
Classifier: Environment :: Web Environment
Classifier: Intended Audience :: Developers
Classifier: Intended Audience :: System Administrators
Classifier: Operating System :: OS Independent
Classifier: Programming Language :: Python :: 2.7
Classifier: Programming Language :: Python :: 3.5
Classifier: Topic :: Software Development :: Build Tools
Classifier: Topic :: System :: Software Distribution
